[
    {
        "characterId": 1,
        "name": "ick"
    },
    {
        "characterId": 2,
        "name": "saki"
    },
    {
        "characterId": 3,
        "name": "hnm"
    },
    {
        "characterId": 4,
        "name": "shiho"
    },
    {
        "characterId": 5,
        "name": "mnr"
    },
    {
        "characterId": 6,
        "name": "hrk"
    },
    {
        "characterId": 7,
        "name": "airi"
    },
    {
        "characterId": 8,
        "name": "szk"
    },
    {
        "characterId": 9,
        "name": "khn"
    },
    {
        "characterId": 10,
        "name": "an"
    },
    {
        "characterId": 11,
        "name": "akito"
    },
    {
        "characterId": 12,
        "name": "toya"
    },
    {
        "characterId": 13,
        "name": "tks"
    },
    {
        "characterId": 14,
        "name": "emu"
    },
    {
        "characterId": 15,
        "name": "nene"
    },
    {
        "characterId": 16,
        "name": "rui"
    },
    {
        "characterId": 17,
        "name": "knd"
    },
    {
        "characterId": 18,
        "name": "mfy"
    },
    {
        "characterId": 19,
        "name": "ena"
    },
    {
        "characterId": 20,
        "name": "mzk"
    },
    {
        "characterId": 21,
        "name": "miku"
    },
    {
        "characterId": 22,
        "name": "rin"
    },
    {
        "characterId": 23,
        "name": "len"
    },
    {
        "characterId": 24,
        "name": "luka"
    },
    {
        "characterId": 25,
        "name": "meiko"
    },
    {
        "characterId": 26,
        "name": "kaito"
    }
]